{"elysia\ud83c\udf73": {"username": "elysia\ud83c\udf73", "chat_id": 242518561, "location": "NUS", "beneficiary": "CHILDREN", "timing": "WEEKLY", "friends": "WITH A GROUP", "other_info": "stub"}, "Nelson": {"username": "Nelson", "chat_id": 674031544, "location": "NUS", "beneficiary": "ELDERLY", "timing": "WEEKLY", "friends": "ALONE", "other_info": "I have a car"}, "wei ning": {"username": "wei ning", "chat_id": 67353321, "location": "SOUTH", "beneficiary": "CHILDREN", "timing": "MONTHLY", "friends": "ALONE", "other_info": "stub"}}